changgelog/__init__.py
changgelog-0.0.1.dist-info/METADATA
changgelog-0.0.1.dist-info/WHEEL
changgelog-0.0.1.dist-info/top_level.txt
changgelog-0.0.1.dist-info/RECORD
