Metadata-Version: 2.1
Name: changgelog
Version: 0.0.1
Summary: changgelog
Home-page: https://github.com/RimoChan/changgelog
Author: RimoChan
Author-email: the@librian.net
License: UNKNOWN
Platform: UNKNOWN
Classifier: Environment :: Win32 (MS Windows)
Classifier: Programming Language :: Python :: 3
